vsrc/sparse_buffer/find_bottom_ptr_impl.sv
module fid_bottom_ptr_impl(
  input  logic [7:0] entry_valid_i,
  input  logic [2:0] bottom_ptr_current,
  output logic [2:0] bottom_ptr_next
);

  logic [7:0] entry_valid_shift;

  assign entry_valid_shift = entry_valid_i >> bottom_ptr_current
                           | entry_valid_i << ('d8 - bottom_ptr_current);

  assign bottom_ptr_next[2:0] = entry_valid_shift[0] ? bottom_ptr_current[2:0]
                              : entry_valid_shift[1] ? bottom_ptr_current[2:0] + 3'd1
                              : entry_valid_shift[2] ? bottom_ptr_current[2:0] + 3'd2
                              : entry_valid_shift[3] ? bottom_ptr_current[2:0] + 3'd3
                              : entry_valid_shift[4] ? bottom_ptr_current[2:0] + 3'd4
                              : entry_valid_shift[5] ? bottom_ptr_current[2:0] + 3'd5
                              : entry_valid_shift[6] ? bottom_ptr_current[2:0] + 3'd6
                              : entry_valid_shift[7] ? bottom_ptr_current[2:0] + 3'd7
                              :                        3'd7; // if has no valid entry set bottom ptr to 7

endmodule

vsrc/sparse_buffer/sparse_buffer.sv
module sparse_buffer #(
  parameter DW   = 8,
  parameter AW   = 3,
  parameter SIZE = 8
)(
  input  logic            clk_i,
  input  logic            rstn_i,
  // Write ports
  input  logic            write_valid_i,
  output logic            write_allowIn_o,
  input  logic [DW-1:0]   write_data_i,
  // Read ports
  input  logic            read_valid_i,
  output logic            read_allowIn_o,
  input  logic [AW-1:0]   read_ptr_i,
  // Read data return ports
  output logic            read_rtn_valid_o,
  input  logic            read_rtn_allowIn_i,
  output logic [DW-1:0]   read_rtn_data_o,
  // Buffer state ports
  output logic [SIZE-1:0] sparse_buffer_valid_o,
  output logic [AW-1:0]   sparse_buffer_bottom_ptr_o
);

  logic [DW-1:0]   sparse_array_In [SIZE-1:0];
  logic [DW-1:0]   sparse_array_Q  [SIZE-1:0];

  logic [SIZE-1:0] sparse_array_valid_In;
  logic [SIZE-1:0] sparse_array_valid_Q;

  logic            write_kickoff;
  logic [AW-1:0]   write_ptr_In;
  logic [AW-1:0]   write_ptr_Q;

  logic            read_kickoff;

  logic [AW-1:0]   bottom_ptr_In;
  logic [AW-1:0]   bottom_ptr_Q;

//---------------------------------------------------------
//                    update write ptr
//---------------------------------------------------------
  assign write_allowIn_o = write_ptr_Q != bottom_ptr_Q;
  assign write_ptr_In = write_ptr_Q + 'd1;
  assign write_kickoff = write_valid_i & write_allowIn_o;

  always_ff @(posedge clk_i or negedge rstn_i) begin
    if (~rstn_i) begin
      write_ptr_Q <= '0;
    end
    else if (write_kickoff) begin
      write_ptr_Q <= write_ptr_In;
    end
  end

//---------------------------------------------------------
//                update sparse array
//---------------------------------------------------------
  always_comb begin
    sparse_array_In = sparse_array_Q;
    if (write_kickoff) begin
      sparse_array_In[write_ptr_Q] = write_data_i; 
    end
  end

  always_ff @(posedge clk_i or negedge rstn_i) begin
    if (~rstn_i) begin
      sparse_array_Q <= '{default: 'd0};
    end
    else begin
      sparse_array_Q <= sparse_array_In;
    end
  end

//---------------------------------------------------------
//                update sparse array valid
//---------------------------------------------------------
  always_comb begin
    sparse_array_valid_In = sparse_array_valid_Q;
    if (write_kickoff) begin
      sparse_array_valid_In[write_ptr_Q] = 1'b1;
    end
    if (read_kickoff) begin
      sparse_array_valid_In[read_ptr_i] = 1'b0;
    end
  end

  always_ff @(posedge clk_i or negedge rstn_i) begin
    if (~rstn_i) begin
      sparse_array_valid_Q <= '0;
    end
    else begin
      sparse_array_valid_Q <= sparse_array_valid_In;
    end
  end

  assign sparse_buffer_valid_o = sparse_array_valid_Q;

  assign sparse_buffer_bottom_ptr_o = bottom_ptr_Q;

//---------------------------------------------------------
//                         read
//---------------------------------------------------------
  assign read_kickoff = read_valid_i & read_allowIn_o;
  assign read_allowIn_o = read_rtn_allowIn_i;

  assign read_rtn_valid_o = read_valid_i
                          ? sparse_array_valid_Q[read_ptr_i]
                          : 1'b0;

  assign read_rtn_data_o = read_valid_i
                         ? sparse_array_Q[read_ptr_i]
                         : 'd0;

//---------------------------------------------------------
//                update bottom ptr
//---------------------------------------------------------

  // Note: this implement is only for 8 Entry.
  fid_bottom_ptr_impl u_fid_bottom_ptr_impl(  
    .entry_valid_i      ( sparse_array_valid_Q[7:0] ),
    .bottom_ptr_current ( bottom_ptr_Q[2:0]         ),
    .bottom_ptr_next    ( bottom_ptr_In[2:0]        )
  );

  always_ff @(posedge clk_i or negedge rstn_i) begin
    if (~rstn_i) begin
      bottom_ptr_Q <= 'd7;
    end
    else begin
      bottom_ptr_Q <= bottom_ptr_In;
    end
  end

endmodule

unit_test/sparse_buffer_wave.vcd
$version Generated by VerilatedVcd $end
$date Tue Oct 15 14:15:40 2024 $end
$timescale 1ps $end

 $scope module TOP $end
  $var wire  1 ; clk_i $end
  $var wire  1 A read_allowIn_o $end
  $var wire  3 B read_ptr_i [2:0] $end
  $var wire  1 D read_rtn_allowIn_i $end
  $var wire  8 E read_rtn_data_o [7:0] $end
  $var wire  1 C read_rtn_valid_o $end
  $var wire  1 @ read_valid_i $end
  $var wire  1 < rstn_i $end
  $var wire  3 G sparse_buffer_bottom_ptr_o [2:0] $end
  $var wire  8 F sparse_buffer_valid_o [7:0] $end
  $var wire  1 > write_allowIn_o $end
  $var wire  8 ? write_data_i [7:0] $end
  $var wire  1 = write_valid_i $end
  $scope module sparse_buffer $end
   $var wire 32 J AW [31:0] $end
   $var wire 32 I DW [31:0] $end
   $var wire 32 I SIZE [31:0] $end
   $var wire  3 8 bottom_ptr_In [2:0] $end
   $var wire  3 9 bottom_ptr_Q [2:0] $end
   $var wire  1 ; clk_i $end
   $var wire  1 A read_allowIn_o $end
   $var wire  1 H read_kickoff $end
   $var wire  3 B read_ptr_i [2:0] $end
   $var wire  1 D read_rtn_allowIn_i $end
   $var wire  8 E read_rtn_data_o [7:0] $end
   $var wire  1 C read_rtn_valid_o $end
   $var wire  1 @ read_valid_i $end
   $var wire  1 < rstn_i $end
   $var wire  8 # sparse_array_In[0] [7:0] $end
   $var wire  8 $ sparse_array_In[1] [7:0] $end
   $var wire  8 % sparse_array_In[2] [7:0] $end
   $var wire  8 & sparse_array_In[3] [7:0] $end
   $var wire  8 ' sparse_array_In[4] [7:0] $end
   $var wire  8 ( sparse_array_In[5] [7:0] $end
   $var wire  8 ) sparse_array_In[6] [7:0] $end
   $var wire  8 * sparse_array_In[7] [7:0] $end
   $var wire  8 - sparse_array_Q[0] [7:0] $end
   $var wire  8 . sparse_array_Q[1] [7:0] $end
   $var wire  8 / sparse_array_Q[2] [7:0] $end
   $var wire  8 0 sparse_array_Q[3] [7:0] $end
   $var wire  8 1 sparse_array_Q[4] [7:0] $end
   $var wire  8 2 sparse_array_Q[5] [7:0] $end
   $var wire  8 3 sparse_array_Q[6] [7:0] $end
   $var wire  8 4 sparse_array_Q[7] [7:0] $end
   $var wire  8 + sparse_array_valid_In [7:0] $end
   $var wire  8 5 sparse_array_valid_Q [7:0] $end
   $var wire  3 G sparse_buffer_bottom_ptr_o [2:0] $end
   $var wire  8 F sparse_buffer_valid_o [7:0] $end
   $var wire  1 > write_allowIn_o $end
   $var wire  8 ? write_data_i [7:0] $end
   $var wire  1 , write_kickoff $end
   $var wire  3 6 write_ptr_In [2:0] $end
   $var wire  3 7 write_ptr_Q [2:0] $end
   $var wire  1 = write_valid_i $end
   $scope module u_fid_bottom_ptr_impl $end
    $var wire  3 9 bottom_ptr_current [2:0] $end
    $var wire  3 8 bottom_ptr_next [2:0] $end
    $var wire  8 5 entry_valid_i [7:0] $end
    $var wire  8 : entry_valid_shift [7:0] $end
   $upscope $end
  $upscope $end
 $upscope $end
$enddefinitions $end


#0
b00000000 #
b00000000 $
b00000000 %
b00000000 &
b00000000 '
b00000000 (
b00000000 )
b00000000 *
b00000000 +
0,
b00000000 -
b00000000 .
b00000000 /
b00000000 0
b00000000 1
b00000000 2
b00000000 3
b00000000 4
b00000000 5
b001 6
b000 7
b111 8
b000 9
b00000000 :
0;
0<
0=
0>
b00000000 ?
0@
0A
b000 B
0C
0D
b00000000 E
b00000000 F
b000 G
0H
b00000000000000000000000000001000 I
b00000000000000000000000000000011 J
#1
b111 9
1;
1>
#2
b00000001 +
1,
0;
1<
1=
#3
b00000011 +
b00000001 5
b010 6
b001 7
b000 8
b00000010 :
1;
b00000001 F
#4
b00000001 $
0;
b00000001 ?
#5
b00000001 %
b00000111 +
b00000001 .
b00000011 5
b011 6
b010 7
b000 9
b00000011 :
1;
b00000011 F
#6
b00000010 %
0;
b00000010 ?
#7
b00000010 &
b00001111 +
b00000010 /
b00000111 5
b100 6
b011 7
b00000111 :
1;
b00000111 F
#8
b00000011 &
0;
b00000011 ?
#9
b00000011 '
b00011111 +
b00000011 0
b00001111 5
b101 6
b100 7
b00001111 :
1;
b00001111 F
#10
b00000100 '
0;
b00000100 ?
#11
b00000100 (
b00111111 +
b00000100 1
b00011111 5
b110 6
b101 7
b00011111 :
1;
b00011111 F
#12
b00000101 (
0;
b00000101 ?
#13
b00000101 )
b01111111 +
b00000101 2
b00111111 5
b111 6
b110 7
b00111111 :
1;
b00111111 F
#14
b00000110 )
0;
b00000110 ?
#15
b00000110 *
b11111111 +
b00000110 3
b01111111 5
b000 6
b111 7
b01111111 :
1;
b01111111 F
#16
b00000111 *
0;
b00000111 ?
#17
0,
b00000111 4
b11111111 5
b001 6
b000 7
b11111111 :
1;
0>
b11111111 F
#18
0;
0=
