vsrc/sparse_buffer/find_bottom_ptr_impl.sv
module fid_bottom_ptr_impl(
  input  logic [7:0] entry_valid_i,
  input  logic [2:0] bottom_ptr_current,
  output logic [2:0] bottom_ptr_next
);

  logic [7:0] entry_valid_shift;

  assign entry_valid_shift = entry_valid_i >> bottom_ptr_current
                           | entry_valid_i << ('d8 - bottom_ptr_current);

  assign bottom_ptr_next[2:0] = entry_valid_shift[0] ? bottom_ptr_current[2:0]
                              : entry_valid_shift[1] ? bottom_ptr_current[2:0] + 3'd1
                              : entry_valid_shift[2] ? bottom_ptr_current[2:0] + 3'd2
                              : entry_valid_shift[3] ? bottom_ptr_current[2:0] + 3'd3
                              : entry_valid_shift[4] ? bottom_ptr_current[2:0] + 3'd4
                              : entry_valid_shift[5] ? bottom_ptr_current[2:0] + 3'd5
                              : entry_valid_shift[6] ? bottom_ptr_current[2:0] + 3'd6
                              : entry_valid_shift[7] ? bottom_ptr_current[2:0] + 3'd7
                              :                        3'd7; // if has no valid entry set bottom ptr to 7

endmodule

vsrc/sparse_buffer/sparse_buffer.sv
module sparse_buffer #(
  parameter DW   = 8,
  parameter AW   = 3,
  parameter SIZE = 8
)(
  input  logic            clk_i,
  input  logic            rstn_i,
  // Write ports
  input  logic            write_valid_i,
  output logic            write_allowIn_o,
  input  logic [DW-1:0]   write_data_i,
  // Read ports
  input  logic            read_valid_i,
  output logic            read_allowIn_o,
  input  logic [AW-1:0]   read_ptr_i,
  // Read data return ports
  output logic            read_rtn_valid_o,
  input  logic            read_rtn_allowIn_i,
  output logic [DW-1:0]   read_rtn_data_o,
  // Buffer state ports
  output logic [SIZE-1:0] sparse_buffer_valid_o,
  output logic [AW-1:0]   sparse_buffer_bottom_ptr_o
);

  logic [DW-1:0]   sparse_array_In [SIZE-1:0];
  logic [DW-1:0]   sparse_array_Q  [SIZE-1:0];

  logic [SIZE-1:0] sparse_array_valid_In;
  logic [SIZE-1:0] sparse_array_valid_Q;

  logic            write_kickoff;
  logic [AW-1:0]   write_ptr_In;
  logic [AW-1:0]   write_ptr_Q;

  logic            read_kickoff;

  logic [AW-1:0]   bottom_ptr_In;
  logic [AW-1:0]   bottom_ptr_Q;

//---------------------------------------------------------
//                    update write ptr
//---------------------------------------------------------
  assign write_allowIn_o = write_ptr_Q != bottom_ptr_Q;
  assign write_ptr_In = write_ptr_Q + 'd1;
  assign write_kickoff = write_valid_i & write_allowIn_o;

  always_ff @(posedge clk_i or negedge rstn_i) begin
    if (~rstn_i) begin
      write_ptr_Q <= '0;
    end
    else if (write_kickoff) begin
      write_ptr_Q <= write_ptr_In;
    end
  end

//---------------------------------------------------------
//                update sparse array
//---------------------------------------------------------
  always_comb begin
    sparse_array_In = sparse_array_Q;
    if (write_kickoff) begin
      sparse_array_In[write_ptr_Q] = write_data_i; 
    end
  end

  always_ff @(posedge clk_i or negedge rstn_i) begin
    if (~rstn_i) begin
      sparse_array_Q <= '{default: 'd0};
    end
    else begin
      sparse_array_Q <= sparse_array_In;
    end
  end

//---------------------------------------------------------
//                update sparse array valid
//---------------------------------------------------------
  always_comb begin
    sparse_array_valid_In = sparse_array_valid_Q;
    if (write_kickoff) begin
      sparse_array_valid_In[write_ptr_Q] = 1'b1;
    end
    if (read_kickoff) begin
      sparse_array_valid_In[read_ptr_i] = 1'b0;
    end
  end

  always_ff @(posedge clk_i or negedge rstn_i) begin
    if (~rstn_i) begin
      sparse_array_valid_Q <= '0;
    end
    else begin
      sparse_array_valid_Q <= sparse_array_valid_In;
    end
  end

  assign sparse_buffer_valid_o = sparse_array_valid_Q;

  assign sparse_buffer_bottom_ptr_o = bottom_ptr_Q;

//---------------------------------------------------------
//                         read
//---------------------------------------------------------
  assign read_kickoff = read_valid_i & read_allowIn_o;
  assign read_allowIn_o = read_rtn_allowIn_i;

  assign read_rtn_valid_o = read_valid_i
                          ? sparse_array_valid_Q[read_ptr_i]
                          : 1'b0;

  assign read_rtn_data_o = read_valid_i
                         ? sparse_array_Q[read_ptr_i]
                         : 'd0;

//---------------------------------------------------------
//                update bottom ptr
//---------------------------------------------------------

  // Note: this implement is only for 8 Entry.
  fid_bottom_ptr_impl u_fid_bottom_ptr_impl(  
    .entry_valid_i      ( sparse_array_valid_Q[7:0] ),
    .bottom_ptr_current ( bottom_ptr_Q[2:0]         ),
    .bottom_ptr_next    ( bottom_ptr_In[2:0]        )
  );

  always_ff @(posedge clk_i or negedge rstn_i) begin
    if (~rstn_i) begin
      bottom_ptr_Q <= 'd7;
    end
    else begin
      bottom_ptr_Q <= bottom_ptr_In;
    end
  end

endmodule

unit_test/sparse_buffer_wave.vcd
$version Generated by VerilatedVcd $end
$date Tue Oct 15 16:19:18 2024 $end
$timescale 1ps $end

 $scope module TOP $end
  $var wire  1 ; clk_i $end
  $var wire  1 A read_allowIn_o $end
  $var wire  3 B read_ptr_i [2:0] $end
  $var wire  1 D read_rtn_allowIn_i $end
  $var wire  8 E read_rtn_data_o [7:0] $end
  $var wire  1 C read_rtn_valid_o $end
  $var wire  1 @ read_valid_i $end
  $var wire  1 < rstn_i $end
  $var wire  3 G sparse_buffer_bottom_ptr_o [2:0] $end
  $var wire  8 F sparse_buffer_valid_o [7:0] $end
  $var wire  1 > write_allowIn_o $end
  $var wire  8 ? write_data_i [7:0] $end
  $var wire  1 = write_valid_i $end
  $scope module sparse_buffer $end
   $var wire 32 J AW [31:0] $end
   $var wire 32 I DW [31:0] $end
   $var wire 32 I SIZE [31:0] $end
   $var wire  3 8 bottom_ptr_In [2:0] $end
   $var wire  3 9 bottom_ptr_Q [2:0] $end
   $var wire  1 ; clk_i $end
   $var wire  1 A read_allowIn_o $end
   $var wire  1 H read_kickoff $end
   $var wire  3 B read_ptr_i [2:0] $end
   $var wire  1 D read_rtn_allowIn_i $end
   $var wire  8 E read_rtn_data_o [7:0] $end
   $var wire  1 C read_rtn_valid_o $end
   $var wire  1 @ read_valid_i $end
   $var wire  1 < rstn_i $end
   $var wire  8 # sparse_array_In[0] [7:0] $end
   $var wire  8 $ sparse_array_In[1] [7:0] $end
   $var wire  8 % sparse_array_In[2] [7:0] $end
   $var wire  8 & sparse_array_In[3] [7:0] $end
   $var wire  8 ' sparse_array_In[4] [7:0] $end
   $var wire  8 ( sparse_array_In[5] [7:0] $end
   $var wire  8 ) sparse_array_In[6] [7:0] $end
   $var wire  8 * sparse_array_In[7] [7:0] $end
   $var wire  8 - sparse_array_Q[0] [7:0] $end
   $var wire  8 . sparse_array_Q[1] [7:0] $end
   $var wire  8 / sparse_array_Q[2] [7:0] $end
   $var wire  8 0 sparse_array_Q[3] [7:0] $end
   $var wire  8 1 sparse_array_Q[4] [7:0] $end
   $var wire  8 2 sparse_array_Q[5] [7:0] $end
   $var wire  8 3 sparse_array_Q[6] [7:0] $end
   $var wire  8 4 sparse_array_Q[7] [7:0] $end
   $var wire  8 + sparse_array_valid_In [7:0] $end
   $var wire  8 5 sparse_array_valid_Q [7:0] $end
   $var wire  3 G sparse_buffer_bottom_ptr_o [2:0] $end
   $var wire  8 F sparse_buffer_valid_o [7:0] $end
   $var wire  1 > write_allowIn_o $end
   $var wire  8 ? write_data_i [7:0] $end
   $var wire  1 , write_kickoff $end
   $var wire  3 6 write_ptr_In [2:0] $end
   $var wire  3 7 write_ptr_Q [2:0] $end
   $var wire  1 = write_valid_i $end
   $scope module u_fid_bottom_ptr_impl $end
    $var wire  3 9 bottom_ptr_current [2:0] $end
    $var wire  3 8 bottom_ptr_next [2:0] $end
    $var wire  8 5 entry_valid_i [7:0] $end
    $var wire  8 : entry_valid_shift [7:0] $end
   $upscope $end
  $upscope $end
 $upscope $end
$enddefinitions $end


#0
b00000000 #
b00000000 $
b00000000 %
b00000000 &
b00000000 '
b00000000 (
b00000000 )
b00000000 *
b00000000 +
0,
b00000000 -
b00000000 .
b00000000 /
b00000000 0
b00000000 1
b00000000 2
b00000000 3
b00000000 4
b00000000 5
b001 6
b000 7
b111 8
b000 9
b00000000 :
0;
0<
0=
0>
b00000000 ?
0@
0A
b000 B
0C
0D
b00000000 E
b00000000 F
b000 G
0H
b00000000000000000000000000001000 I
b00000000000000000000000000000011 J
#1
b111 9
1;
1>
b111 G
#2
b00000001 +
1,
0;
1<
1=
1A
1D
#3
b00000011 +
b00000001 5
b010 6
b001 7
b000 8
b00000010 :
1;
b00000001 F
#4
b00000001 $
0;
b00000001 ?
#5
b00000001 %
b00000111 +
b00000001 .
b00000011 5
b011 6
b010 7
b000 9
b00000011 :
1;
b00000011 F
b000 G
#6
b00000010 %
b00000110 +
0;
b00000010 ?
1@
1C
1H
#7
b00000010 &
b00001110 +
b00000010 /
b00000110 5
b100 6
b011 7
b001 8
b00000110 :
1;
0C
b00000110 F
#8
b00000011 &
0;
b00000011 ?
#9
b00000011 '
b00011110 +
b00000011 0
b00001110 5
b101 6
b100 7
b001 9
b00000111 :
1;
b00001110 F
b001 G
#10
b00000100 '
b00011100 +
0;
b00000100 ?
b001 B
1C
b00000001 E
#11
b00000100 (
b00111100 +
b00000100 1
b00011100 5
b110 6
b101 7
b010 8
b00001110 :
1;
0C
b00011100 F
#12
b00000101 (
0;
b00000101 ?
#13
b00000101 )
b01111100 +
b00000101 2
b00111100 5
b111 6
b110 7
b010 9
b00001111 :
1;
b00111100 F
b010 G
#14
b00000110 )
b01111000 +
0;
b00000110 ?
b010 B
1C
b00000010 E
#15
b00000110 *
b11111000 +
b00000110 3
b01111000 5
b000 6
b111 7
b011 8
b00011110 :
1;
0C
b01111000 F
#16
b00000111 *
0;
b00000111 ?
#17
b00000111 #
b11111001 +
b00000111 4
b11111000 5
b001 6
b000 7
b011 9
b00011111 :
1;
b11111000 F
b011 G
#18
b00001000 #
b11110001 +
0;
b00001000 ?
b011 B
1C
b00000011 E
#19
b00001000 $
b11110011 +
b00001000 -
b11110001 5
b010 6
b001 7
b100 8
b00111110 :
1;
0C
b11110001 F
#20
b00001001 $
0;
b00001001 ?
#21
b00001001 %
b11110111 +
b00001001 .
b11110011 5
b011 6
b010 7
b100 9
b00111111 :
1;
b11110011 F
b100 G
#22
b00001010 %
b11100111 +
0;
b00001010 ?
b100 B
1C
b00000100 E
#23
b00001010 &
b11101111 +
b00001010 /
b11100111 5
b100 6
b011 7
b101 8
b01111110 :
1;
0C
b11100111 F
#24
b00001011 &
0;
b00001011 ?
#25
b00001011 '
b00001011 0
b11101111 5
b101 6
b100 7
b101 9
b01111111 :
1;
b11101111 F
b101 G
#26
b00001100 '
b11011111 +
0;
b00001100 ?
b101 B
1C
b00000101 E
#27
0,
b00001100 1
b11011111 5
b110 6
b101 7
b110 8
b11111110 :
1;
0>
0C
b11011111 F
#28
0;
0=
#29
b110 9
b01111111 :
1;
1>
b110 G
#30
b00001110 (
b10111111 +
1,
0;
1=
b00001110 ?
b110 B
1C
b00000110 E
#31
0,
b00001110 2
b10111111 5
b111 6
b110 7
b111 8
b11111110 :
1;
0>
0C
b10111111 F
#32
0;
0=
#33
b111 9
b01111111 :
1;
1>
b111 G
#34
b00010000 )
b01111111 +
1,
0;
1=
b00010000 ?
b111 B
1C
b00000111 E
#35
0,
b00010000 3
b01111111 5
b000 6
b111 7
b000 8
b11111110 :
1;
0>
0C
b01111111 F
#36
0;
0=
#37
b000 9
b01111111 :
1;
1>
b000 G
#38
b00010010 *
b11111110 +
1,
0;
1=
b00010010 ?
b000 B
1C
b00001000 E
#39
0,
b00010010 4
b11111110 5
b001 6
b000 7
b001 8
b11111110 :
1;
0>
0C
b11111110 F
#40
0;
0=
#41
b001 9
b01111111 :
1;
1>
b001 G
#42
b00010100 #
b11111101 +
1,
0;
1=
b00010100 ?
b001 B
1C
b00001001 E
#43
0,
b00010100 -
b11111101 5
b010 6
b001 7
b010 8
b11111110 :
1;
0>
0C
b11111101 F
#44
0;
0=
#45
b010 9
b01111111 :
1;
1>
b010 G
#46
b00010110 $
b11111011 +
1,
0;
1=
b00010110 ?
b010 B
1C
b00001010 E
#47
0,
b00010110 .
b11111011 5
b011 6
b010 7
b011 8
b11111110 :
1;
0>
0C
b11111011 F
#48
0;
0=
#49
b011 9
b01111111 :
1;
1>
b011 G
#50
b00011000 %
b11110111 +
1,
0;
1=
b00011000 ?
b011 B
1C
b00001011 E
#51
0,
b00011000 /
b11110111 5
b100 6
b011 7
b100 8
b11111110 :
1;
0>
0C
b11110111 F
#52
0;
0=
#53
b100 9
b01111111 :
1;
1>
b100 G
#54
b00011010 &
b11101111 +
1,
0;
1=
b00011010 ?
b100 B
1C
b00001100 E
#55
0,
b00011010 0
b11101111 5
b101 6
b100 7
b101 8
b11111110 :
1;
0>
0C
b11101111 F
#56
0;
0=
#57
b101 9
b01111111 :
1;
1>
b101 G
#58
b00011100 '
b11011111 +
1,
0;
1=
b00011100 ?
b101 B
1C
b00001110 E
#59
0,
b00011100 1
b11011111 5
b110 6
b101 7
b110 8
b11111110 :
1;
0>
0C
b11011111 F
#60
0;
0=
#61
b110 9
b01111111 :
1;
1>
b110 G
#62
b00011110 (
b10111111 +
1,
0;
1=
b00011110 ?
b110 B
1C
b00010000 E
#63
0,
b00011110 2
b10111111 5
b111 6
b110 7
b111 8
b11111110 :
1;
0>
0C
b10111111 F
#64
0;
0=
#65
b111 9
b01111111 :
1;
1>
b111 G
#66
b00100000 )
b01111111 +
1,
0;
1=
b00100000 ?
b111 B
1C
b00010010 E
#67
0,
b00100000 3
b01111111 5
b000 6
b111 7
b000 8
b11111110 :
1;
0>
0C
b01111111 F
#68
0;
0=
#69
b000 9
b01111111 :
1;
1>
b000 G
#70
b00100010 *
b11111110 +
1,
0;
1=
b00100010 ?
b000 B
1C
b00010100 E
#71
0,
b00100010 4
b11111110 5
b001 6
b000 7
b001 8
b11111110 :
1;
0>
0C
b11111110 F
#72
0;
0=
#73
b001 9
b01111111 :
1;
1>
b001 G
#74
b00100100 #
b11111101 +
1,
0;
1=
b00100100 ?
b001 B
1C
b00010110 E
#75
0,
b00100100 -
b11111101 5
b010 6
b001 7
b010 8
b11111110 :
1;
0>
0C
b11111101 F
#76
0;
0=
#77
b010 9
b01111111 :
1;
1>
b010 G
#78
b00100110 $
b11111011 +
1,
0;
1=
b00100110 ?
b010 B
1C
b00011000 E
#79
0,
b00100110 .
b11111011 5
b011 6
b010 7
b011 8
b11111110 :
1;
0>
0C
b11111011 F
#80
0;
0=
#81
b011 9
b01111111 :
1;
1>
b011 G
#82
b00101000 %
b11110111 +
1,
0;
1=
b00101000 ?
b011 B
1C
b00011010 E
#83
0,
b00101000 /
b11110111 5
b100 6
b011 7
b100 8
b11111110 :
1;
0>
0C
b11110111 F
#84
0;
0=
#85
b100 9
b01111111 :
1;
1>
b100 G
#86
b00101010 &
b11101111 +
1,
0;
1=
b00101010 ?
b100 B
1C
b00011100 E
#87
0,
b00101010 0
b11101111 5
b101 6
b100 7
b101 8
b11111110 :
1;
0>
0C
b11101111 F
#88
0;
0=
#89
b101 9
b01111111 :
1;
1>
b101 G
#90
b00101100 '
b11011111 +
1,
0;
1=
b00101100 ?
b101 B
1C
b00011110 E
#91
0,
b00101100 1
b11011111 5
b110 6
b101 7
b110 8
b11111110 :
1;
0>
0C
b11011111 F
#92
0;
0=
#93
b110 9
b01111111 :
1;
1>
b110 G
#94
b00101110 (
b10111111 +
1,
0;
1=
b00101110 ?
b110 B
1C
b00100000 E
#95
0,
b00101110 2
b10111111 5
b111 6
b110 7
b111 8
b11111110 :
1;
0>
0C
b10111111 F
#96
0;
0=
#97
b111 9
b01111111 :
1;
1>
b111 G
#98
b00110000 )
b01111111 +
1,
0;
1=
b00110000 ?
b111 B
1C
b00100010 E
#99
0,
b00110000 3
b01111111 5
b000 6
b111 7
b000 8
b11111110 :
1;
0>
0C
b01111111 F
#100
0;
0=
#101
b000 9
b01111111 :
1;
1>
b000 G
#102
b00110010 *
b11111110 +
1,
0;
1=
b00110010 ?
b000 B
1C
b00100100 E
#103
0,
b00110010 4
b11111110 5
b001 6
b000 7
b001 8
b11111110 :
1;
0>
0C
b11111110 F
#104
0;
0=
#105
b001 9
b01111111 :
1;
1>
b001 G
#106
b00110100 #
b11111101 +
1,
0;
1=
b00110100 ?
b001 B
1C
b00100110 E
#107
0,
b00110100 -
b11111101 5
b010 6
b001 7
b010 8
b11111110 :
1;
0>
0C
b11111101 F
#108
0;
0=
#109
b010 9
b01111111 :
1;
1>
b010 G
#110
b00110110 $
b11111011 +
1,
0;
1=
b00110110 ?
b010 B
1C
b00101000 E
#111
0,
b00110110 .
b11111011 5
b011 6
b010 7
b011 8
b11111110 :
1;
0>
0C
b11111011 F
#112
0;
0=
#113
b011 9
b01111111 :
1;
1>
b011 G
#114
b00111000 %
b11110111 +
1,
0;
1=
b00111000 ?
b011 B
1C
b00101010 E
#115
0,
b00111000 /
b11110111 5
b100 6
b011 7
b100 8
b11111110 :
1;
0>
0C
b11110111 F
#116
0;
0=
#117
b100 9
b01111111 :
1;
1>
b100 G
#118
b00111010 &
b11101111 +
1,
0;
1=
b00111010 ?
b100 B
1C
b00101100 E
#119
0,
b00111010 0
b11101111 5
b101 6
b100 7
b101 8
b11111110 :
1;
0>
0C
b11101111 F
#120
0;
0=
#121
b101 9
b01111111 :
1;
1>
b101 G
#122
b00111100 '
b11011111 +
1,
0;
1=
b00111100 ?
b101 B
1C
b00101110 E
#123
0,
b00111100 1
b11011111 5
b110 6
b101 7
b110 8
b11111110 :
1;
0>
0C
b11011111 F
#124
0;
0=
#125
b110 9
b01111111 :
1;
1>
b110 G
#126
b00111110 (
b10111111 +
1,
0;
1=
b00111110 ?
b110 B
1C
b00110000 E
#127
0,
b00111110 2
b10111111 5
b111 6
b110 7
b111 8
b11111110 :
1;
0>
0C
b10111111 F
#128
0;
0=
#129
b111 9
b01111111 :
1;
1>
b111 G
#130
b01000000 )
b01111111 +
1,
0;
1=
b01000000 ?
b111 B
1C
b00110010 E
#131
0,
b01000000 3
b01111111 5
b000 6
b111 7
b000 8
b11111110 :
1;
0>
0C
b01111111 F
#132
0;
0=
#133
b000 9
b01111111 :
1;
1>
b000 G
#134
b01000010 *
b11111110 +
1,
0;
1=
b01000010 ?
b000 B
1C
b00110100 E
#135
0,
b01000010 4
b11111110 5
b001 6
b000 7
b001 8
b11111110 :
1;
0>
0C
b11111110 F
#136
0;
0=
#137
b001 9
b01111111 :
1;
1>
b001 G
#138
b01000100 #
b11111101 +
1,
0;
1=
b01000100 ?
b001 B
1C
b00110110 E
#139
0,
b01000100 -
b11111101 5
b010 6
b001 7
b010 8
b11111110 :
1;
0>
0C
b11111101 F
#140
0;
0=
#141
b010 9
b01111111 :
1;
1>
b010 G
#142
b01000110 $
b11111011 +
1,
0;
1=
b01000110 ?
b010 B
1C
b00111000 E
#143
0,
b01000110 .
b11111011 5
b011 6
b010 7
b011 8
b11111110 :
1;
0>
0C
b11111011 F
#144
0;
0=
#145
b011 9
b01111111 :
1;
1>
b011 G
#146
b01001000 %
b11110111 +
1,
0;
1=
b01001000 ?
b011 B
1C
b00111010 E
#147
0,
b01001000 /
b11110111 5
b100 6
b011 7
b100 8
b11111110 :
1;
0>
0C
b11110111 F
#148
0;
0=
#149
b100 9
b01111111 :
1;
1>
b100 G
#150
b01001010 &
b11101111 +
1,
0;
1=
b01001010 ?
b100 B
1C
b00111100 E
#151
0,
b01001010 0
b11101111 5
b101 6
b100 7
b101 8
b11111110 :
1;
0>
0C
b11101111 F
#152
0;
0=
#153
b101 9
b01111111 :
1;
1>
b101 G
#154
b01001100 '
b11011111 +
1,
0;
1=
b01001100 ?
b101 B
1C
b00111110 E
#155
0,
b01001100 1
b11011111 5
b110 6
b101 7
b110 8
b11111110 :
1;
0>
0C
b11011111 F
#156
0;
0=
#157
b110 9
b01111111 :
1;
1>
b110 G
#158
b01001110 (
b10111111 +
1,
0;
1=
b01001110 ?
b110 B
1C
b01000000 E
#159
0,
b01001110 2
b10111111 5
b111 6
b110 7
b111 8
b11111110 :
1;
0>
0C
b10111111 F
#160
0;
0=
#161
b111 9
b01111111 :
1;
1>
b111 G
#162
b01010000 )
b01111111 +
1,
0;
1=
b01010000 ?
b111 B
1C
b01000010 E
#163
0,
b01010000 3
b01111111 5
b000 6
b111 7
b000 8
b11111110 :
1;
0>
0C
b01111111 F
#164
0;
0=
#165
b000 9
b01111111 :
1;
1>
b000 G
#166
b01010010 *
b11111110 +
1,
0;
1=
b01010010 ?
b000 B
1C
b01000100 E
#167
0,
b01010010 4
b11111110 5
b001 6
b000 7
b001 8
b11111110 :
1;
0>
0C
b11111110 F
#168
0;
0=
#169
b001 9
b01111111 :
1;
1>
b001 G
#170
b01010100 #
b11111101 +
1,
0;
1=
b01010100 ?
b001 B
1C
b01000110 E
#171
0,
b01010100 -
b11111101 5
b010 6
b001 7
b010 8
b11111110 :
1;
0>
0C
b11111101 F
#172
0;
0=
#173
b010 9
b01111111 :
1;
1>
b010 G
#174
b01010110 $
b11111011 +
1,
0;
1=
b01010110 ?
b010 B
1C
b01001000 E
#175
0,
b01010110 .
b11111011 5
b011 6
b010 7
b011 8
b11111110 :
1;
0>
0C
b11111011 F
#176
0;
0=
#177
b011 9
b01111111 :
1;
1>
b011 G
#178
b01011000 %
b11110111 +
1,
0;
1=
b01011000 ?
b011 B
1C
b01001010 E
#179
0,
b01011000 /
b11110111 5
b100 6
b011 7
b100 8
b11111110 :
1;
0>
0C
b11110111 F
#180
0;
0=
#181
b100 9
b01111111 :
1;
1>
b100 G
#182
b01011010 &
b11101111 +
1,
0;
1=
b01011010 ?
b100 B
1C
b01001100 E
#183
0,
b01011010 0
b11101111 5
b101 6
b100 7
b101 8
b11111110 :
1;
0>
0C
b11101111 F
#184
0;
0=
#185
b101 9
b01111111 :
1;
1>
b101 G
#186
b01011100 '
b11011111 +
1,
0;
1=
b01011100 ?
b101 B
1C
b01001110 E
#187
0,
b01011100 1
b11011111 5
b110 6
b101 7
b110 8
b11111110 :
1;
0>
0C
b11011111 F
#188
0;
0=
#189
b110 9
b01111111 :
1;
1>
b110 G
#190
b01011110 (
b10111111 +
1,
0;
1=
b01011110 ?
b110 B
1C
b01010000 E
#191
0,
b01011110 2
b10111111 5
b111 6
b110 7
b111 8
b11111110 :
1;
0>
0C
b10111111 F
#192
0;
0=
#193
b111 9
b01111111 :
1;
1>
b111 G
#194
b01100000 )
b01111111 +
1,
0;
1=
b01100000 ?
b111 B
1C
b01010010 E
#195
0,
b01100000 3
b01111111 5
b000 6
b111 7
b000 8
b11111110 :
1;
0>
0C
b01111111 F
#196
0;
0=
#197
b000 9
b01111111 :
1;
1>
b000 G
#198
b01100010 *
b11111110 +
1,
0;
1=
b01100010 ?
b000 B
1C
b01010100 E
#199
0,
b01100010 4
b11111110 5
b001 6
b000 7
b001 8
b11111110 :
1;
0>
0C
b11111110 F
#200
0;
0=
#201
b001 9
b01111111 :
1;
1>
b001 G
